Workbook

Sheet Resumen
C2: Facturación: | D2: =IF(Detalle!F2="",Detalle!E2,Detalle!F2) -> Kaltemp | E2: 46213
C4: Servicio | D4: Envíos
C5: Servicio Enviame Connect | D5: =COUNTIF(Detalle!I:I,"Servicio Enviame Connect") -> 0 | E5: =SUMIF(Detalle!I:I,"Servicio Enviame Connect",Detalle!W:W) -> 0
C6: Servicio Enviame Connect Plus | D6: =COUNTIF(Detalle!I:I,"Servicio Enviame Connect Plus") -> 0 | E6: =SUMIF(Detalle!I:I,"Servicio Enviame Connect Plus",Detalle!W:W) -> 0
C7: Servicio Enviame Distribucion | D7: =COUNTIF(Detalle!I:I,"Servicio Enviame Distribucion") -> 1099 | E7: =SUMIF(Detalle!I:I,"Servicio Enviame Distribucion",Detalle!W:W) -> 14955747
C8: Servicio Enviame Enviatrack | D8: =COUNTIF(Detalle!I:I,"Servicio Enviame Enviatrack") -> 0 | E8: =SUMIF(Detalle!I:I,"Servicio Enviame Enviatrack",Detalle!W:W) -> 0
C9: Servicio Enviame Flex | D9: =COUNTIF(Detalle!I:I,"Servicio Enviame Flex") -> 0 | E9: =SUMIF(Detalle!I:I,"Servicio Enviame Flex",Detalle!W:W) -> 0
C10: Servicio Enviame Marketcenter | D10: =COUNTIF(Detalle!I:I,"Servicio Enviame Marketcenter") -> 0 | E10: =SUMIF(Detalle!I:I,"Servicio Enviame Marketcenter",Detalle!W:W) -> 0
C11: Servicio Enviame Notificaciones | D11: =COUNTIF(Detalle!I:I,"Servicio Enviame Notificaciones") -> 0 | E11: =SUMIF(Detalle!I:I,"Servicio Enviame Notificaciones",Detalle!W:W) -> 0
C12: Servicio Enviame por Pagar | D12: =COUNTIF(Detalle!I:I,"Servicio Enviame por Pagar") -> 0 | E12: =SUMIF(Detalle!I:I,"Servicio Enviame por Pagar",Detalle!W:W) -> 0
C13: Servicio Enviame Retiros | D13: =COUNTIF(Detalle!I:I,"Servicio Enviame Retiros") -> 0 | E13: =SUMIF(Detalle!I:I,"Servicio Enviame Retiros",Detalle!W:W) -> 0
C14: Servicio Enviame Soporte Tecnico | D14: =COUNTIF(Detalle!I:I,"Servicio Enviame Soporte Tecnico") -> 0 | E14: =SUMIF(Detalle!I:I,"Servicio Enviame Soporte Tecnico",Detalle!W:W) -> 0
C15: Servicio Enviame Modelo Cross Dock | D15: =COUNTIF(Detalle!I:I,"Servicio Enviame Modelo Cross Dock") -> 0 | E15: =SUMIF(Detalle!I:I,"Sevicio Enviame Modelo Cross Dock",Detalle!W:W) -> 0
C16: Servicio Enviame Adicional | D16: =COUNTIF(Detalle!I:I,"Servicio Enviame Adicional") -> 0 | E16: =SUMIF(Detalle!I:I,"Servicio Enviame Adicional",Detalle!W:W) -> 0
C17: Servicio Enviame Marketplace | D17: =COUNTIF(Detalle!I:I,"Servicio Enviame Marketplace") -> 0 | E17: =SUMIF(Detalle!I:I,"Servicio Enviame Marketplace",Detalle!W:W) -> 0
C18: Servicio Enviame Logistica Inversa | D18: =COUNTIF(Detalle!I:I,"Servicio Enviame Logistica Inversa") -> 0 | E18: =SUMIF(Detalle!I:I,"Servicio Enviame Logistica Inversa",Detalle!W:W) -> 0
C19: Subtotal | E19: =SUM(E5:E18) -> 14955747
C21: IVA | E21: =E19*0.19 -> 2841592
C22: Total | E22: =+E19+E21 -> 17797339

Sheet Detalle
A1: company_id | B1: id | C1: imported_id | D1: tracking_number | E1: company | F1: mkp | G1: carrier | H1: carrier_code | I1: contract_type | J1: carrier_service_name | K1: status | L1: comment | M1: name_person | N1: dir_origen | O1: com_origen | P1: dir_destino | Q1: com_destino | R1: created_at | S1: Columna1 | T1: peso informado por carrier | U1: precio | V1: seguro | W1: total
A2: 15741 | B2: 456252281 | C2: 39665 | D2: 272510410 | E2: Kaltemp | G2: STARKEN | H2: SKN | I2: Servicio Enviame Distribucion | J2: Normal | K2: En Reparto | L2: EN REPARTO | M2: Ivo Roman Luza | N2: Av. Américo Vespucio 400 | O2: Pudahuel | P2: Av Alessandri 1513, casa 54 cond Alto San Esteban, san Esteban | Q2: San Esteban | R2: 2026-06-04 16:20 | S2: 46177 | T2: 222.4 | U2: 72657.56 | V2: 11999.94 | W2: 84657.5
A3: 15741 | B3: 456225725 | C3: 55756 | D3: 272156576 | E3: Kaltemp | G3: STARKEN | H3: SKN | I3: Servicio Enviame Distribucion | J3: Normal | K3: En Reparto | L3: EN REPARTO | M3: Raciel Medina | N3: Av. Américo Vespucio 400 | O3: Pudahuel | P3: Alonso de Ercilla, 7688, Floor Casa H | Q3: La Florida | R3: 2026-06-04 12:11 | S3: 46177 | T3: 2.1 | U3: 5816 | V3: 0 | W3: 5816
A4: 15741 | B4: 456993228 | C4: 56679 | D4: 272834220 | E4: Kaltemp | G4: STARKEN | H4: SKN | I4: Servicio Enviame Distribucion | J4: Normal | K4: Entregado | L4: NOMBRE RETIRA: RUBEN SALINAA . RUT RETIRA: 7614607-1 | M4: Ruben Salinas Lopez | N4: Av. Américo Vespucio 400 | O4: Pudahuel | P4: Rene Quitral 0700 | Q4: Maipú | R4: 2026-06-23 12:18 | S4: 46196 | T4: 2.1 | U4: 5816 | V4: 0 | W4: 5816
A5: 15741 | B5: 456993013 | C5: 56672 | D5: 272834145 | E5: Kaltemp | G5: STARKEN | H5: SKN | I5: Servicio Enviame Distribucion | J5: Normal | K5: Entregado | L5: NOMBRE RETIRA: ROSA CORREA . RUT RETIRA: 20188220-6 | M5: Ximena Bacarreza Rodriguez | N5: Av. Américo Vespucio 400 | O5: Pudahuel | P5: Senegal Norte, 2522 | Q5: Vitacura | R5: 2026-06-23 12:13 | S5: 46196 | T5: 2.1 | U5: 5816 | V5: 0 | W5: 5816
A6: 15741 | B6: 457025291 | C6: 56716 | D6: 272898597 | E6: Kaltemp | G6: STARKEN | H6: SKN | I6: Servicio Enviame Distribucion | J6: Normal | K6: Entregado | L6: NOMBRE RETIRA: ERICK ACEVEDO . RUT RETIRA: 19032467-2 | M6: Eduardo Campos | N6: Av. Américo Vespucio 400 | O6: Pudahuel | P6: Camino Real 120 PDI, SAN FRANCISCO DE MOSTAZAL | Q6: Mostazal | R6: 2026-06-24 11:49 | S6: 46197 | T6: 2.55 | U6: 11780 | V6: 0 | W6: 11780
A7: 15741 | B7: 457005586 | C7: 56710 | D7: 272861739 | E7: Kaltemp | G7: STARKEN | H7: SKN | I7: Servicio Enviame Distribucion | J7: Normal | K7: Entregado | L7: NOMBRE RETIRA: CARLOTA HONZALES U RUT RETIRA: 7694932-8 | M7: Francisca Flores | N7: Av. Américo Vespucio 400 | O7: Pudahuel | P7: Jose Bordes 6549 | Q7: La Reina | R7: 2026-06-23 17:30 | S7: 46196 | T7: 2.1 | U7: 5816 | V7: 0 | W7: 5816
A8: 15741 | B8: 457005360 | C8: 56707 | D8: 272861665 | E8: Kaltemp | G8: STARKEN | H8: SKN | I8: Servicio Enviame Distribucion | J8: Normal | K8: Entregado | L8: NOMBRE RETIRA: CLAUDIA ACEVEDO . RUT RETIRA: 20347999-9 | M8: Claudia Acevedo Campos | N8: Av. Américo Vespucio 400 | O8: Pudahuel | P8: San Francisco 2217 local 461 entrar por Bio Bio 839 | Q8: Santiago | R8: 2026-06-23 17:28 | S8: 46196 | T8: 4.74 | U8: 6450 | V8: 0 | W8: 6450
A9: 15741 | B9: 457005315 | C9: 56705 | D9: 272861643 | E9: Kaltemp | G9: STARKEN | H9: SKN | I9: Servicio Enviame Distribucion | J9: Normal | K9: Entregado | L9: NOMBRE RETIRA: MARIA ROJAS AAA RUT RETIRA: 7774196-8 | M9: IGNACIO CONCHA | N9: Av. Américo Vespucio 400 | O9: Pudahuel | P9: Victoria 664 Entregar a Inés Aravena | Q9: San Bernardo | R9: 2026-06-23 17:27 | S9: 46196 | T9: 2.1 | U9: 5816 | V9: 0 | W9: 5816
A10: 15741 | B10: 457005202 | C10: 56701 | D10: 272861510 | E10: Kaltemp | G10: STARKEN | H10: SKN | I10: Servicio Enviame Distribucion | J10: Normal | K10: Entregado | L10: NOMBRE RETIRA: CAROLINA CUNA A RUT RETIRA: 13667112-K | M10: Carolina Acuna | N10: Av. Américo Vespucio 400 | O10: Pudahuel | P10: Nuestra Señora de Genoveva 9585 Entre Enrique Olivares y Santa Valentina | Q10: La Florida | R10: 2026-06-23 17:24 | S10: 46196 | T10: 2 | U10: 5504 | V10: 0 | W10: 5504
A11: 15741 | B11: 457025443 | C11: 56719 | D11: 272898617 | E11: Kaltemp | G11: STARKEN | H11: SKN | I11: Servicio Enviame Distribucion | J11: Normal | K11: Entregado | L11: NOMBRE RETIRA: RODRIGO V D RUT RETIRA: 11421733-6 | M11: RODRIGO ANTONIO VELASQUEZ | N11: Av. Américo Vespucio 400 | O11: Pudahuel | P11: parque de la hacienda 6359 | Q11: Peñalolén | R11: 2026-06-24 11:54 | S11: 46197 | T11: 2.1 | U11: 5816 | V11: 0 | W11: 5816
A12: 15741 | B12: 457025494 | C12: 56723 | D12: 272898649 | E12: Kaltemp | G12: STARKEN | H12: SKN | I12: Servicio Enviame Distribucion | J12: Normal | K12: Entrega parcial | L12: ENTREGA PARCIAL | M12: Maria Cecilia Donoso | N12: Av. Américo Vespucio 400 | O12: Pudahuel | P12: Locarno 4252 | Q12: Lo Barnechea | R12: 2026-06-24 11:55 | S12: 46197 | T12: 32.4 | U12: 13488 | V12: 0 | W12: 13488
A13: 15741 | B13: 457005284 | C13: 56704 | D13: 272861624 | E13: Kaltemp | G13: STARKEN | H13: SKN | I13: Servicio Enviame Distribucion | J13: Normal | K13: Entregado | L13: NOMBRE RETIRA: ALBIER . . RUT RETIRA: 22154314-9 | M13: Sebastian Bravo | N13: Av. Américo Vespucio 400 | O13: Pudahuel | P13: Av Luis Thayer Ojeda 1525 1302 Dejar en conserjeria | Q13: Providencia | R13: 2026-06-23 17:26 | S13: 46196 | T13: 4.74 | U13: 6450 | V13: 0 | W13: 6450
... A1100: 15741 | B1100: 455249919 | C1100: 18402 | D1100: 2294560096 | E1100: Kaltemp | G1100: BLUEXPRESS | H1100: BLX | I1100: Servicio Enviame Distribucion | J1100: Express | K1100: Entregado | L1100: ENTREGADO | M1100: DIEGO MEDINA CEBALLOS | N1100: Av. Américo Vespucio 400 | O1100: Pudahuel | P1100: Av Rukan 315 casa 114 Colina, Santiago, Chile | Q1100: Colina | R1100: 2026-05-25 11:28 | S1100: 46167 | T1100: 9.83 | U1100: 5465 | V1100: 0 | W1100: 5465
